{
   "services": [
        {
            "refName": "hive", 
            "serviceConfigs": [
                {"name": "hiveserver2_enable_ssl", "value": "true"}, 
                {"name": "hiveserver2_keystore_path", "value": "/var/lib/cloudera-scm-agent/agent-cert/cm-auto-host_keystore.jks"}, 
                {"name": "hiveserver2_keystore_password", "value": "Cloudera123"},
                {"name": "ssl_client_truststore_location", "value": "/var/lib/cloudera-scm-agent/agent-cert/cm-auto-global_truststore.jks"},
                {"name": "hiveserver2_truststore_file", "value": "/var/lib/cloudera-scm-agent/agent-cert/cm-auto-global_truststore.jks"}, 
                {"name": "hiveserver2_truststore_password", "value": "Cloudera123"}
            ], 
            "serviceType": "HIVE"
        }, 
        {
            "serviceType": "HIVE_ON_TEZ",
            "refName": "hive_on_tez", 
            "roleConfigGroups": [
                {
                    "refName": "hive_on_tez-HIVESERVER2-1", 
                    "roleType": "HIVESERVER2",
                    "base": false, 
                    "configs": [
                        {"name": "ssl_server_keystore_location", "value": "/var/lib/cloudera-scm-agent/agent-cert/cm-auto-host_keystore.jks"}, 
                        {"name": "ssl_server_keystore_password", "value": "Cloudera123"}, 
                        {"name": "ssl_enabled", "value": "true"}
                    ]
                }
            ], 
            "serviceConfigs": [
                {"name": "hiveserver2_truststore_file", "value": "/var/lib/cloudera-scm-agent/agent-cert/cm-auto-global_truststore.jks"},
                {"name": "hiveserver2_enable_ssl", "value": "true"},
                {"name": "hiveserver2_keystore_password", "value": "Cloudera123"},
                {"name": "hiveserver2_keystore_path", "value": "/var/lib/cloudera-scm-agent/agent-cert/cm-auto-host_keystore.jks"},
                {"name": "hiveserver2_truststore_password", "value": "Cloudera123"}
            ]
        }, 
        {
            "serviceType": "ATLAS",
            "refName": "atlas", 
            "roleConfigGroups": [
                {
                    "refName": "atlas-ATLAS_SERVER-1", 
                    "roleType": "ATLAS_SERVER",
                    "base": false, 
                    "configs": [
                        {"name": "ssl_client_truststore_location", "value": "/var/lib/cloudera-scm-agent/agent-cert/cm-auto-global_truststore.jks"},
                        {"name": "ssl_server_keystore_location", "value": "/var/lib/cloudera-scm-agent/agent-cert/cm-auto-host_keystore.jks"},
                        {"name": "ssl_client_truststore_password", "value": "Cloudera123"},
                        {"name": "ssl_enabled", "value": "true"}, 
                        {"name": "ssl_server_keystore_keypassword", "value": "Cloudera123"}, 
                        {"name": "ssl_server_keystore_password", "value": "Cloudera123"}
                    ]
                }
            ]
        }, 
        {
            "serviceType": "KUDU",
            "refName": "kudu", 
            "roleConfigGroups": [
                {
                    "refName": "kudu-KUDU_TSERVER-1", 
                    "roleType": "KUDU_TSERVER",
                    "base": false, 
                    "configs": [
                        {"name": "ssl_server_ca_certificate_location", "value": "/var/lib/cloudera-scm-agent/agent-cert/cm-auto-in_cluster_ca_cert.pem"},
                        {"name": "ssl_enabled", "value": "true"},
                        {"name": "ssl_server_privatekey_password", "value": "Cloudera123"},
                        {"name": "ssl_server_privatekey_location", "value": "/var/lib/cloudera-scm-agent/agent-cert/cm-auto-host_key.pem"},
                        {"name": "ssl_server_certificate_location", "value": "/var/lib/cloudera-scm-agent/agent-cert/cm-auto-host_cert_chain.pem"}
                    ]
                }, 
                {
                    "refName": "kudu-KUDU_MASTER-1", 
                    "roleType": "KUDU_MASTER",
                    "base": false, 
                    "configs": [
                        {"name": "ssl_client_truststore_location", "value": "/var/lib/cloudera-scm-agent/agent-cert/cm-auto-global_truststore.jks"}, 
                        {"name": "ssl_server_ca_certificate_location", "value": "/var/lib/cloudera-scm-agent/agent-cert/cm-auto-in_cluster_ca_cert.pem"}, 
                        {"name": "ssl_client_truststore_password", "value": "Cloudera123"}, 
                        {"name": "ssl_enabled", "value": "true"}, 
                        {"name": "ssl_server_privatekey_location", "value": "/var/lib/cloudera-scm-agent/agent-cert/cm-auto-host_key.pem"}, 
                        {"name": "ssl_server_privatekey_password", "value": "Cloudera123"},
                        {"name": "ssl_server_certificate_location", "value": "/var/lib/cloudera-scm-agent/agent-cert/cm-auto-host_cert_chain.pem"}
                    ]
                }
            ]
        }, 
        {
            "serviceType": "OZONE",
            "refName": "ozone", 
            "roleConfigGroups": [
                {
                    "refName": "ozone-STORAGE_CONTAINER_MANAGER-1", 
                    "roleType": "STORAGE_CONTAINER_MANAGER",
                    "base": false, 
                    "configs": [
                        {"name": "ssl_client_truststore_location", "value": "/var/lib/cloudera-scm-agent/agent-cert/cm-auto-global_truststore.jks"}, 
                        {"name": "ssl_server_keystore_location", "value": "/var/lib/cloudera-scm-agent/agent-cert/cm-auto-host_keystore.jks"}, 
                        {"name": "ssl_client_truststore_password", "value": "Cloudera123"}, 
                        {"name": "ssl_enabled", "value": "true"}, 
                        {"name": "ssl_server_keystore_keypassword", "value": "Cloudera123"}, 
                        {"name": "ssl_server_keystore_password", "value": "Cloudera123"}
                    ]
                }, 
                {
                    "refName": "ozone-GATEWAY-1", 
                    "roleType": "GATEWAY",
                    "base": false, 
                    "configs": [
                        {"name": "ssl_client_truststore_location", "value": "/var/lib/cloudera-scm-agent/agent-cert/cm-auto-global_truststore.jks"}, 
                        {"name": "ssl_client_truststore_password", "value": "Cloudera123"}
                    ]
                }, 
                {
                    "refName": "ozone-OZONE_RECON-1", 
                    "roleType": "OZONE_RECON",
                    "base": false, 
                    "configs": [
                        {"name": "ssl_client_truststore_location", "value": "/var/lib/cloudera-scm-agent/agent-cert/cm-auto-global_truststore.jks"}, 
                        {"name": "ssl_server_keystore_location", "value": "/var/lib/cloudera-scm-agent/agent-cert/cm-auto-host_keystore.jks"}, 
                        {"name": "ssl_client_truststore_password", "value": "Cloudera123"}, 
                        {"name": "ssl_enabled", "value": "true"}, 
                        {"name": "ssl_server_keystore_keypassword", "value": "Cloudera123"}, 
                        {"name": "ssl_server_keystore_password", "value": "Cloudera123"}
                    ]
                }, 
                {
                    "refName": "ozone-OZONE_MANAGER-1", 
                    "roleType": "OZONE_MANAGER",
                    "base": false, 
                    "configs": [
                        {"name": "ssl_client_truststore_location", "value": "/var/lib/cloudera-scm-agent/agent-cert/cm-auto-global_truststore.jks"}, 
                        {"name": "ssl_server_keystore_location", "value": "/var/lib/cloudera-scm-agent/agent-cert/cm-auto-host_keystore.jks"}, 
                        {"name": "ssl_client_truststore_password", "value": "Cloudera123"}, 
                        {"name": "ssl_enabled", "value": "true"}, 
                        {"name": "ssl_server_keystore_keypassword", "value": "Cloudera123"}, 
                        {"name": "ssl_server_keystore_password", "value": "Cloudera123"}
                    ]
                }, 
                {
                    "refName": "ozone-OZONE_DATANODE-1", 
                    "roleType": "OZONE_DATANODE",
                    "base": false, 
                    "configs": [
                        {"name": "ssl_client_truststore_location", "value": "/var/lib/cloudera-scm-agent/agent-cert/cm-auto-global_truststore.jks"},
                        {"name": "ssl_server_keystore_location", "value": "/var/lib/cloudera-scm-agent/agent-cert/cm-auto-host_keystore.jks"},
                        {"name": "ssl_client_truststore_password", "value": "Cloudera123"},
                        {"name": "ssl_enabled", "value": "true"}, 
                        {"name": "ssl_server_keystore_keypassword", "value": "Cloudera123"}, 
                        {"name": "ssl_server_keystore_password", "value": "Cloudera123"}
                    ]
                }, 
                {
                    "refName": "ozone-S3_GATEWAY-1", 
                    "roleType": "S3_GATEWAY",
                    "base": false, 
                    "configs": [
                        {"name": "ssl_client_truststore_location", "value": "/var/lib/cloudera-scm-agent/agent-cert/cm-auto-global_truststore.jks"},
                        {"name": "ssl_server_keystore_location", "value": "/var/lib/cloudera-scm-agent/agent-cert/cm-auto-host_keystore.jks"},
                        {"name": "ssl_client_truststore_password", "value": "Cloudera123"},
                        {"name": "ssl_enabled", "value": "true"},
                        {"name": "ssl_server_keystore_keypassword", "value": "Cloudera123"},
                        {"name": "ssl_server_keystore_password", "value": "Cloudera123"}
                    ]
                }
            ]
        }, 
        {
            "serviceType": "CRUISE_CONTROL",
            "refName": "cruise_control", 
            "roleConfigGroups": [
                {
                    "refName": "cruise_control-CRUISE_CONTROL_SERVER-1",
                    "roleType": "CRUISE_CONTROL_SERVER",
                    "base": false, 
                    "configs": [
                        {"name": "ssl_client_truststore_location", "value": "/var/lib/cloudera-scm-agent/agent-cert/cm-auto-global_truststore.jks"},
                        {"name": "ssl_server_keystore_location", "value": "/var/lib/cloudera-scm-agent/agent-cert/cm-auto-host_keystore.jks"},
                        {"name": "ssl_client_truststore_password", "value": "Cloudera123"},
                        {"name": "ssl_enabled", "value": "true"},
                        {"name": "ssl_server_keystore_keypassword", "value": "Cloudera123"},
                        {"name": "ssl_server_keystore_password", "value": "Cloudera123"}
                    ]
                }
            ]
        }, 
        {
            "serviceType": "SPARK_ON_YARN",
            "refName": "spark", 
            "roleConfigGroups": [
                {
                    "refName": "spark-SPARK_YARN_HISTORY_SERVER-1",
                    "roleType": "SPARK_YARN_HISTORY_SERVER",
                    "base": false, 
                    "configs": [
                        {"name": "ssl_server_keystore_location", "value": "/var/lib/cloudera-scm-agent/agent-cert/cm-auto-host_keystore.jks"},
                        {"name": "ssl_enabled", "value": "true"},
                        {"name": "ssl_server_keystore_password", "value": "Cloudera123"}
                    ]
                }
            ]
        }, 
        {
            "serviceType": "SOLR",
            "refName": "solr", 
            "serviceConfigs": [
                {"name": "solr_https_truststore_file", "value": "/var/lib/cloudera-scm-agent/agent-cert/cm-auto-global_truststore.jks"},
                {"name": "solr_https_truststore_password", "value": "Cloudera123"},
                {"name": "solr_https_keystore_file", "value": "/var/lib/cloudera-scm-agent/agent-cert/cm-auto-host_keystore.jks"},
                {"name": "solr_https_keystore_password", "value": "Cloudera123"},
                {"name": "solr_use_ssl", "value": "true"}
            ]
        }, 
        {
            "serviceType": "SCHEMAREGISTRY",
            "refName": "schemaregistry", 
            "roleConfigGroups": [
                {
                    "refName": "schemaregistry-SCHEMA_REGISTRY_SERVER-1", 
                    "roleType": "SCHEMA_REGISTRY_SERVER",
                    "base": false, 
                    "configs": [
                        {"name": "ssl_server_keystore_location", "value": "/var/lib/cloudera-scm-agent/agent-cert/cm-auto-host_keystore.jks"},
                        {"name": "ssl_client_truststore_password", "value": "Cloudera123"},
                        {"name": "ssl_server_keystore_password", "value": "Cloudera123"},
                        {"name": "ssl_client_truststore_location", "value": "/var/lib/cloudera-scm-agent/agent-cert/cm-auto-global_truststore.jks"},
                        {"name": "ssl_enabled", "value": "true"}
                    ]
                }
            ]
        }, 
        {
            "serviceType": "STREAMS_MESSAGING_MANAGER",
            "refName": "streams_messaging_manager", 
            "roleConfigGroups": [
                {
                    "refName": "streams_messaging_manager-STREAMS_MESSAGING_MANAGER_UI-1", 
                    "roleType": "STREAMS_MESSAGING_MANAGER_UI",
                    "base": false, 
                    "configs": [
                        {"name": "ssl_server_privatekey_location", "value": "/var/lib/cloudera-scm-agent/agent-cert/cm-auto-host_key.pem"}, 
                        {"name": "ssl_server_certificate_location", "value": "/var/lib/cloudera-scm-agent/agent-cert/cm-auto-host_key_cert_chain.pem"},
                        {"name": "ssl_client_truststore_location", "value": "/var/lib/cloudera-scm-agent/agent-cert/cm-auto-global_truststore.jks"},
                        {"name": "ssl_server_ca_certificate_location", "value": "/var/lib/cloudera-scm-agent/agent-cert/cm-auto-in_cluster_ca_cert.pem"},
                        {"name": "ssl_enabled", "value": "true"},
                        {"name": "ssl_server_privatekey_password", "value": "Cloudera123"}
                    ]
                }, 
                {
                    "refName": "streams_messaging_manager-STREAMS_MESSAGING_MANAGER_SERVER-1", 
                    "roleType": "STREAMS_MESSAGING_MANAGER_SERVER",
                    "base": false, 
                    "configs": [
                        {"name": "ssl_server_keystore_location", "value": "/var/lib/cloudera-scm-agent/agent-cert/cm-auto-host_keystore.jks"},
                        {"name": "ssl_client_truststore_password", "value": "Cloudera123"},
                        {"name": "ssl_server_keystore_password", "value": "Cloudera123"},
                        {"name": "ssl_client_truststore_location", "value": "/var/lib/cloudera-scm-agent/agent-cert/cm-auto-global_truststore.jks"},
                        {"name": "ssl_enabled", "value": "true"},
                        {"name": "ssl_server_keystore_keypassword", "value": "Cloudera123"}
                    ]
                }
            ]
        }, 
        {
            "serviceType": "HBASE",
            "refName": "hbase", 
            "roleConfigGroups": [
                {
                    "refName": "hbase-MASTER-1",
                    "roleType": "MASTER",
                    "base": false, 
                    "configs": [
                        {"name": "master_truststore_password", "value": "Cloudera123"},
                        {"name": "master_truststore_file", "value": "/var/lib/cloudera-scm-agent/agent-cert/cm-auto-global_truststore.jks"}
                    ]
                }, 
                {
                    "refName": "hbase-HBASETHRIFTSERVER-1", 
                    "roleType": "HBASETHRIFTSERVER",
                    "base": false, 
                    "configs": [
                        {"name": "hbase_thriftserver_http_keystore_password", "value": "Cloudera123"},
                        {"name": "hbase_thriftserver_http_keystore_keypassword", "value": "Cloudera123"},
                        {"name": "hbase_thriftserver_http_keystore_file", "value": "/var/lib/cloudera-scm-agent/agent-cert/cm-auto-host_keystore.jks"},
                        {"name": "hbase_thriftserver_http_use_ssl", "value": "true"}
                    ]
                }, 
                {
                    "refName": "hbase-REGIONSERVER-1",
                    "roleType": "REGIONSERVER",
                    "base": false, 
                    "configs": [
                        {"name": "regionserver_truststore_password", "value": "Cloudera123"},
                        {"name": "regionserver_truststore_file", "value": "/var/lib/cloudera-scm-agent/agent-cert/cm-auto-global_truststore.jks"}
                    ]
                }
            ], 
            "serviceConfigs": [
                {"name": "ssl_server_keystore_keypassword", "value": "Cloudera123"},
                {"name": "ssl_server_keystore_location", "value": "/var/lib/cloudera-scm-agent/agent-cert/cm-auto-host_keystore.jks"},
                {"name": "ssl_server_keystore_password", "value": "Cloudera123"},
                {"name": "hbase_hadoop_ssl_enabled", "value": "true"}
            ]
        }, 
        {
            "serviceType": "ZOOKEEPER",
            "refName": "zookeeper", 
            "roleConfigGroups": [
                {
                    "refName": "zookeeper-SERVER-1", 
                    "roleType": "SERVER",
                    "base": false, 
                    "configs": [
                        {"name": "jmx_tls_truststore_password", "value": "Cloudera123"}, 
                        {"name": "jmx_tls_client_auth_enabled", "value": "true"}, 
                        {"name": "jmx_tls_enabled", "value": "true"}, 
                        {"name": "jmx_tls_truststore", "value": "/var/lib/cloudera-scm-agent/agent-cert/cm-auto-global_truststore.jks"},
                        {"name": "jmx_tls_keystore", "value": "/var/lib/cloudera-scm-agent/agent-cert/cm-auto-host_keystore.jks"},
                        {"name": "jmx_tls_keystore_password", "value": "Cloudera123"}
                    ]
                }
            ], 
            "serviceConfigs": [
                {"name": "zookeeper_tls_truststore_password", "value": "Cloudera123"},
                {"name": "zookeeper_tls_truststore", "value": "/var/lib/cloudera-scm-agent/agent-cert/cm-auto-global_truststore.jks"},
                {"name": "zookeeper_tls_keystore_password", "value": "Cloudera123"},
                {"name": "zookeeper_tls_keystore", "value": "/var/lib/cloudera-scm-agent/agent-cert/cm-auto-host_keystore.jks"},
                {"name": "zookeeper_tls_enabled", "value": "true"}
            ]
        }, 
        {
            "serviceType": "OOZIE",
            "refName": "oozie", 
            "roleConfigGroups": [
                {
                    "refName": "oozie-OOZIE_SERVER-1",
                    "roleType": "OOZIE_SERVER",
                    "base": false, 
                    "configs": [
                        {"name": "oozie_https_keystore_file", "value": "/var/lib/cloudera-scm-agent/agent-cert/cm-auto-host_keystore.jks"},
                        {"name": "oozie_zookeeper_https_truststore_file", "value": "/var/lib/cloudera-scm-agent/agent-cert/cm-auto-global_truststore.jks"},
                        {"name": "oozie_https_keystore_password", "value": "Cloudera123"},
                        {"name": "oozie_zookeeper_https_keystore_password", "value": "Cloudera123"},
                        {"name": "oozie_https_truststore_file", "value": "/var/lib/cloudera-scm-agent/agent-cert/cm-auto-global_truststore.jks"},
                        {"name": "oozie_https_truststore_password", "value": "Cloudera123"},
                        {"name": "oozie_zookeeper_https_keystore_file", "value": "/var/lib/cloudera-scm-agent/agent-cert/cm-auto-host_keystore.jks"},
                        {"name": "oozie_zookeeper_https_truststore_password", "value": "Cloudera123"}
                    ]
                }
            ], 
            "serviceConfigs": [
                {"name": "oozie_use_ssl", "value": "true"}
            ]
        },
        {
            "refName": "zeppelin", 
            "roleConfigGroups": [
                {
                    "base": false, 
                    "configs": [
                        {"name": "ssl_client_truststore_location", "value": "/var/lib/cloudera-scm-agent/agent-cert/cm-auto-global_truststore.jks"},
                        {"name": "ssl_server_keystore_location", "value": "/var/lib/cloudera-scm-agent/agent-cert/cm-auto-host_keystore.jks"},
                        {"name": "ssl_client_truststore_password", "value": "Cloudera123"},
                        {"name": "ssl_enabled", "value": "true"},
                        {"name": "ssl_server_keystore_password", "value": "Cloudera123"}
                    ], 
                    "refName": "zeppelin-ZEPPELIN_SERVER-1", 
                    "roleType": "ZEPPELIN_SERVER"
                }
            ], 
            "serviceType": "ZEPPELIN"
        }, 
        {
            "serviceType": "IMPALA",
            "refName": "impala", 
            "roleConfigGroups": [
                {
                    "refName": "impala-CATALOGSERVER-1", 
                    "roleType": "CATALOGSERVER",
                    "base": false, 
                    "configs": [
                        {"name": "webserver_private_key_password_cmd", "value": "Cloudera123"}, 
                        {"name": "webserver_private_key_file", "value": "/var/lib/cloudera-scm-agent/agent-cert/cm-auto-host_key.pem"}, 
                        {"name": "webserver_certificate_file", "value": "/var/lib/cloudera-scm-agent/agent-cert/cm-auto-host_cert_chain.pem"}
                    ]
                }, 
                {
                    "refName": "impala-STATESTORE-1", 
                    "roleType": "STATESTORE",
                    "base": false, 
                    "configs": [
                        {"name": "webserver_private_key_password_cmd", "value": "Cloudera123"}, 
                        {"name": "webserver_private_key_file", "value": "/var/lib/cloudera-scm-agent/agent-cert/cm-auto-host_key.pem"}, 
                        {"name": "webserver_certificate_file", "value": "/var/lib/cloudera-scm-agent/agent-cert/cm-auto-host_cert_chain.pem"}
                    ]
                }, 
                {
                    "refName": "impala-IMPALAD-1", 
                    "roleType": "IMPALAD",
                    "base": false, 
                    "configs": [
                        {"name": "webserver_private_key_password_cmd", "value": "Cloudera123"},
                        {"name": "webserver_private_key_file", "value": "/var/lib/cloudera-scm-agent/agent-cert/cm-auto-host_key.pem"},
                        {"name": "webserver_certificate_file", "value": "/var/lib/cloudera-scm-agent/agent-cert/cm-auto-host_cert_chain.pem"}
                    ]
                }
            ], 
            "serviceConfigs": [
                {"name": "ssl_client_ca_certificate", "value": "/var/lib/cloudera-scm-agent/agent-cert/cm-auto-in_cluster_ca_cert.pem"},
                {"name": "impala_truststore_file", "value": "/var/lib/cloudera-scm-agent/agent-cert/cm-auto-global_truststore.jks"},
                {"name": "ssl_private_key", "value": "/var/lib/cloudera-scm-agent/agent-cert/cm-auto-host_key.pem"},
                {"name": "ssl_server_certificate", "value": "/var/lib/cloudera-scm-agent/agent-cert/cm-auto-host_cert_chain.pem"},
                {"name": "impala_truststore_password", "value": "Cloudera123"},
                {"name": "client_services_ssl_enabled", "value": "true"},
                {"name": "ssl_private_key_password", "value": "Cloudera123"}
            ]
        }, 
        {
            "serviceType": "LIVY",
            "refName": "livy", 
            "roleConfigGroups": [
                {
                    "base": false, 
                    "configs": [
                        {"name": "ssl_server_keystore_location", "value": "/var/lib/cloudera-scm-agent/agent-cert/cm-auto-host_keystore.jks"},
                        {"name": "ssl_enabled", "value": "true"},
                        {"name": "ssl_server_keystore_password", "value": "Cloudera123"}
                    ], 
                    "refName": "livy-LIVY_SERVER-1", 
                    "roleType": "LIVY_SERVER"
                }, 
                {
                    "refName": "livy-GATEWAY-1", 
                    "roleType": "GATEWAY",
                    "base": false, 
                    "configs": [
                        {"name": "ssl_client_truststore_location", "value": "/var/lib/cloudera-scm-agent/agent-cert/cm-auto-global_truststore.jks"},
                        {"name": "ssl_client_truststore_password", "value": "Cloudera123"}
                    ]
                }
            ]
        }, 
        {
            "serviceType": "PHOENIX",
            "refName": "phoenix", 
            "roleConfigGroups": [
                {
                    "refName": "phoenix-PHOENIX_QUERY_SERVER-1", 
                    "roleType": "PHOENIX_QUERY_SERVER",
                    "base": false, 
                    "configs": [
                        {"name": "ssl_client_truststore_location", "value": "/var/lib/cloudera-scm-agent/agent-cert/cm-auto-global_truststore.jks"},
                        {"name": "ssl_server_keystore_location", "value": "/var/lib/cloudera-scm-agent/agent-cert/cm-auto-host_keystore.jks"},
                        {"name": "ssl_client_truststore_password","value": "Cloudera123"},
                        {"name": "ssl_enabled", "value": "true"},
                        {"name": "ssl_server_keystore_password", "value": "Cloudera123"}
                    ]
                }
            ]
        }, 
        {
            "serviceType": "QUEUEMANAGER",
            "refName": "queuemanager", 
            "roleConfigGroups": [
                {
                    "refName": "queuemanager-QUEUEMANAGER_WEBAPP-1", 
                    "roleType": "QUEUEMANAGER_WEBAPP",
                    "base": false, 
                    "configs": [
                        {"name": "ssl_client_truststore_location", "value": "/var/lib/cloudera-scm-agent/agent-cert/cm-auto-global_truststore.jks"},
                        {"name": "ssl_server_keystore_location", "value": "/var/lib/cloudera-scm-agent/agent-cert/cm-auto-host_keystore.jks"},
                        {"name": "ssl_client_truststore_password", "value": "Cloudera123"}, 
                        {"name": "ssl_enabled", "value": "true"},
                        {"name": "ssl_server_keystore_password", "value": "Cloudera123"}
                    ]
                }, 
                {
                    "refName": "queuemanager-QUEUEMANAGER_STORE-1", 
                    "roleType": "QUEUEMANAGER_STORE",
                    "base": false, 
                    "configs": [
                        {"name": "ssl_server_keystore_location", "value": "/var/lib/cloudera-scm-agent/agent-cert/cm-auto-host_keystore.jks"},
                        {"name": "ssl_enabled", "value": "true"},
                        {"name": "ssl_server_keystore_password", "value": "Cloudera123"}
                    ]
                }
            ]
        }, 
        {
            "serviceType": "STREAMS_REPLICATION_MANAGER",
            "refName": "streams_replication_manager", 
            "roleConfigGroups": [
                {
                    "refName": "streams_replication_manager-STREAMS_REPLICATION_MANAGER_SERVICE-1", 
                    "roleType": "STREAMS_REPLICATION_MANAGER_SERVICE",
                    "base": false, 
                    "configs": [
                        {"name": "ssl_client_truststore_location", "value": "/var/lib/cloudera-scm-agent/agent-cert/cm-auto-global_truststore.jks"},
                        {"name": "ssl_server_keystore_location", "value": "/var/lib/cloudera-scm-agent/agent-cert/cm-auto-host_keystore.jks"},
                        {"name": "ssl_client_truststore_password", "value": "Cloudera123"},
                        {"name": "ssl_enabled", "value": "true"},
                        {"name": "ssl_server_keystore_keypassword", "value": "Cloudera123"},
                        {"name": "ssl_server_keystore_password", "value": "Cloudera123"}
                    ]
                }, 
                {
                    "refName": "streams_replication_manager-STREAMS_REPLICATION_MANAGER_DRIVER-1",
                    "roleType": "STREAMS_REPLICATION_MANAGER_DRIVER",
                    "base": false, 
                    "configs": [
                        {"name": "ssl_client_truststore_location", "value": "/var/lib/cloudera-scm-agent/agent-cert/cm-auto-global_truststore.jks"},
                        {"name": "ssl_server_keystore_location", "value": "/var/lib/cloudera-scm-agent/agent-cert/cm-auto-host_keystore.jks"},
                        {"name": "ssl_client_truststore_password", "value": "Cloudera123"},
                        {"name": "ssl_enabled", "value": "true"},
                        {"name": "ssl_server_keystore_keypassword", "value": "Cloudera123"},
                        {"name": "ssl_server_keystore_password", "value": "Cloudera123"}
                    ]
                }
            ]
        }, 
        {
            "refName": "kafka", 
            "roleConfigGroups": [
                {
                    "refName": "kafka-KAFKA_BROKER-1",
                    "roleType": "KAFKA_BROKER",
                    "base": false, 
                    "configs": [
                        {"name": "ssl_client_truststore_location","value": "/var/lib/cloudera-scm-agent/agent-cert/cm-auto-global_truststore.jks"},
                        {"name": "ssl_server_keystore_location","value": "/var/lib/cloudera-scm-agent/agent-cert/cm-auto-host_keystore.jks"},
                        {"name": "ssl_client_truststore_password","value": "Cloudera123"},
                        {"name": "ssl_enabled", "value": "true"},
                        {"name": "ssl_server_keystore_keypassword", "value": "Cloudera123"},
                        {"name": "ssl_server_keystore_password", "value": "Cloudera123"}
                    ]
                },
                {
                    "base": false, 
                    "configs": [
                        {"name": "ssl_client_truststore_location", "value": "/var/lib/cloudera-scm-agent/agent-cert/cm-auto-global_truststore.jks"},
                        {"name": "ssl_server_keystore_location", "value": "/var/lib/cloudera-scm-agent/agent-cert/cm-auto-host_keystore.jks"},
                        {"name": "ssl_client_truststore_password", "value": "Cloudera123"},
                        {"name": "ssl_enabled", "value": "true"},
                        {"name": "ssl_server_keystore_keypassword", "value": "Cloudera123"},
                        {"name": "ssl_server_keystore_password", "value": "Cloudera123"}
                    ], 
                    "refName": "kafka-KAFKA_CONNECT-1",
                    "roleType": "KAFKA_CONNECT"
                }
            ], 
            "serviceType": "KAFKA"
        }, 
        {
            "serviceType": "HDFS",
            "refName": "hdfs", 
            "roleConfigGroups": [
                {
                    "refName": "hdfs-NAMENODE-2",
                    "roleType": "NAMENODE",
                    "base": false, 
                    "configs": [
                        {"name": "namenode_truststore_password", "value": "Cloudera123"},
                        {"name": "namenode_truststore_file", "value": "/var/lib/cloudera-scm-agent/agent-cert/cm-auto-global_truststore.jks"}
                    ]
                }
            ], 
            "serviceConfigs": [
                {"name": "hdfs_hadoop_ssl_enabled", "value": "true"},
                {"name": "ssl_client_truststore_location", "value": "/var/lib/cloudera-scm-agent/agent-cert/cm-auto-global_truststore.jks"},
                {"name": "ssl_client_truststore_password", "value": "Cloudera123"},
                {"name": "hadoop_group_mapping_ldap_keystore", "value": "/var/lib/cloudera-scm-agent/agent-cert/cm-auto-host_keystore.jks"},
                {"name": "hadoop_group_mapping_ldap_keystore_passwd", "value": "Cloudera123"},
                {"name": "ssl_server_keystore_password", "value": "Cloudera123"},
                {"name": "ssl_server_keystore_keypassword", "value": "Cloudera123"},
                {"name": "hadoop_group_mapping_ldap_use_ssl", "value": "true"},
                {"name": "ssl_server_keystore_location", "value": "/var/lib/cloudera-scm-agent/agent-cert/cm-auto-host_keystore.jks"}
            ]
        }, 
        {
            "serviceType": "HUE",
            "refName": "hue", 
            "roleConfigGroups": [
                {
                    "refName": "hue-HUE_SERVER-1", 
                    "roleType": "HUE_SERVER",
                    "base": false, 
                    "configs": [
                        {"name": "ssl_certificate", "value": "/var/lib/cloudera-scm-agent/agent-cert/cm-auto-host_cert_chain.pem"}, 
                        {"name": "ssl_private_key_password", "value": "Cloudera123"}, 
                        {"name": "ssl_cacerts", "value": "/var/lib/cloudera-scm-agent/agent-cert/cm-auto-in_cluster_ca_cert.pem"}, 
                        {"name": "ssl_enable", "value": "true"}, 
                        {"name": "ssl_private_key", "value": "/var/lib/cloudera-scm-agent/agent-cert/cm-auto-host_key.pem"}
                    ]
                }, 
                {
                    "refName": "hue-HUE_LOAD_BALANCER-1", 
                    "roleType": "HUE_LOAD_BALANCER",
                    "base": false, 
                    "configs": [
                        {"name": "ssl_certificate", "value": "/var/lib/cloudera-scm-agent/agent-cert/cm-auto-host_cert_chain.pem"}, 
                        {"name": "passphrasefile_location", "value": "/var/lib/cloudera-scm-agent/agent-cert/cm-auto-host_key.pw"}, 
                        {"name": "ssl_certificate_key", "value": "/var/lib/cloudera-scm-agent/agent-cert/cm-auto-host_key.pem"}
                    ]
                }
            ]
        }, 
        {
            "serviceType": "YARN",
            "refName": "yarn", 
            "serviceConfigs": [
                {"name": "ssl_server_keystore_password", "value": "Cloudera123"}, 
                {"name": "ssl_client_truststore_location", "value": "/var/lib/cloudera-scm-agent/agent-cert/cm-auto-global_truststore.jks"}, 
                {"name": "ssl_client_truststore_password", "value": "Cloudera123"}, 
                {"name": "ssl_server_keystore_location", "value": "/var/lib/cloudera-scm-agent/agent-cert/cm-auto-host_keystore.jks"}, 
                {"name": "ssl_server_keystore_keypassword", "value": "Cloudera123"}
            ]
        }
    ]
}